<?xml version="1.0" encoding="UTF-8" standalone="yes"?>
<dsp:drawing xmlns:dgm="http://schemas.openxmlformats.org/drawingml/2006/diagram" xmlns:dsp="http://schemas.microsoft.com/office/drawing/2008/diagram" xmlns:a="http://schemas.openxmlformats.org/drawingml/2006/main"><dsp:spTree><dsp:nvGrpSpPr><dsp:cNvPr id="0" name=""/><dsp:cNvGrpSpPr/></dsp:nvGrpSpPr><dsp:grpSpPr/><dsp:sp modelId="{778FFBFB-E551-4741-A05E-E0377EE72CCB}"><dsp:nvSpPr><dsp:cNvPr id="0" name=""/><dsp:cNvSpPr/></dsp:nvSpPr><dsp:spPr><a:xfrm><a:off x="0" y="1045"/><a:ext cx="5192078" cy="0"/></a:xfrm><a:prstGeom prst="line"><a:avLst/></a:prstGeom><a:solidFill><a:schemeClr val="lt1"><a:hueOff val="0"/><a:satOff val="0"/><a:lumOff val="0"/><a:alphaOff val="0"/></a:schemeClr></a:solidFill><a:ln w="25400" cap="flat" cmpd="sng" algn="ctr"><a:solidFill><a:schemeClr val="accent6"><a:shade val="80000"/><a:hueOff val="0"/><a:satOff val="0"/><a:lumOff val="0"/><a:alphaOff val="0"/></a:schemeClr></a:solidFill><a:prstDash val="solid"/></a:ln><a:effectLst><a:outerShdw blurRad="40000" dist="20000" dir="5400000" rotWithShape="0"><a:srgbClr val="000000"><a:alpha val="38000"/></a:srgbClr></a:outerShdw></a:effectLst></dsp:spPr><dsp:style><a:lnRef idx="2"><a:scrgbClr r="0" g="0" b="0"/></a:lnRef><a:fillRef idx="1"><a:scrgbClr r="0" g="0" b="0"/></a:fillRef><a:effectRef idx="1"><a:scrgbClr r="0" g="0" b="0"/></a:effectRef><a:fontRef idx="minor"><a:schemeClr val="lt1"/></a:fontRef></dsp:style></dsp:sp><dsp:sp modelId="{D20549EB-0F84-6E42-8F2D-DB84369227C0}"><dsp:nvSpPr><dsp:cNvPr id="0" name=""/><dsp:cNvSpPr/></dsp:nvSpPr><dsp:spPr><a:xfrm><a:off x="0" y="1045"/><a:ext cx="5192078" cy="356559"/></a:xfrm><a:prstGeom prst="rect"><a:avLst/></a:prstGeom><a:noFill/><a:ln><a:noFill/></a:ln><a:effectLst/></dsp:spPr><dsp:style><a:lnRef idx="0"><a:scrgbClr r="0" g="0" b="0"/></a:lnRef><a:fillRef idx="0"><a:scrgbClr r="0" g="0" b="0"/></a:fillRef><a:effectRef idx="0"><a:scrgbClr r="0" g="0" b="0"/></a:effectRef><a:fontRef idx="minor"/></dsp:style><dsp:txBody><a:bodyPr spcFirstLastPara="0" vert="horz" wrap="square" lIns="53340" tIns="53340" rIns="53340" bIns="53340" numCol="1" spcCol="1270" anchor="t" anchorCtr="0"><a:noAutofit/></a:bodyPr><a:lstStyle/><a:p><a:pPr marL="0" lvl="0" indent="0" algn="l" defTabSz="622300"><a:lnSpc><a:spcPct val="90000"/></a:lnSpc><a:spcBef><a:spcPct val="0"/></a:spcBef><a:spcAft><a:spcPct val="35000"/></a:spcAft><a:buNone/></a:pPr><a:r><a:rPr lang="en-US" sz="1400" kern="1200" dirty="0"><a:latin typeface="Arial" panose="020B0604020202020204" pitchFamily="34" charset="0"/><a:cs typeface="Arial" panose="020B0604020202020204" pitchFamily="34" charset="0"/></a:rPr><a:t>Design ML system architecture for different use cases</a:t></a:r></a:p></dsp:txBody><dsp:txXfrm><a:off x="0" y="1045"/><a:ext cx="5192078" cy="356559"/></dsp:txXfrm></dsp:sp><dsp:sp modelId="{7FE31048-77DF-AE44-A7D4-0D5D75E69FF4}"><dsp:nvSpPr><dsp:cNvPr id="0" name=""/><dsp:cNvSpPr/></dsp:nvSpPr><dsp:spPr><a:xfrm><a:off x="0" y="357605"/><a:ext cx="5192078" cy="0"/></a:xfrm><a:prstGeom prst="line"><a:avLst/></a:prstGeom><a:solidFill><a:schemeClr val="lt1"><a:hueOff val="0"/><a:satOff val="0"/><a:lumOff val="0"/><a:alphaOff val="0"/></a:schemeClr></a:solidFill><a:ln w="25400" cap="flat" cmpd="sng" algn="ctr"><a:solidFill><a:schemeClr val="accent6"><a:shade val="80000"/><a:hueOff val="0"/><a:satOff val="0"/><a:lumOff val="0"/><a:alphaOff val="0"/></a:schemeClr></a:solidFill><a:prstDash val="solid"/></a:ln><a:effectLst><a:outerShdw blurRad="40000" dist="20000" dir="5400000" rotWithShape="0"><a:srgbClr val="000000"><a:alpha val="38000"/></a:srgbClr></a:outerShdw></a:effectLst></dsp:spPr><dsp:style><a:lnRef idx="2"><a:scrgbClr r="0" g="0" b="0"/></a:lnRef><a:fillRef idx="1"><a:scrgbClr r="0" g="0" b="0"/></a:fillRef><a:effectRef idx="1"><a:scrgbClr r="0" g="0" b="0"/></a:effectRef><a:fontRef idx="minor"><a:schemeClr val="lt1"/></a:fontRef></dsp:style></dsp:sp><dsp:sp modelId="{8F8B8630-111E-A246-BC0D-B9293798361E}"><dsp:nvSpPr><dsp:cNvPr id="0" name=""/><dsp:cNvSpPr/></dsp:nvSpPr><dsp:spPr><a:xfrm><a:off x="0" y="357605"/><a:ext cx="5192078" cy="356559"/></a:xfrm><a:prstGeom prst="rect"><a:avLst/></a:prstGeom><a:noFill/><a:ln><a:noFill/></a:ln><a:effectLst/></dsp:spPr><dsp:style><a:lnRef idx="0"><a:scrgbClr r="0" g="0" b="0"/></a:lnRef><a:fillRef idx="0"><a:scrgbClr r="0" g="0" b="0"/></a:fillRef><a:effectRef idx="0"><a:scrgbClr r="0" g="0" b="0"/></a:effectRef><a:fontRef idx="minor"/></dsp:style><dsp:txBody><a:bodyPr spcFirstLastPara="0" vert="horz" wrap="square" lIns="53340" tIns="53340" rIns="53340" bIns="53340" numCol="1" spcCol="1270" anchor="t" anchorCtr="0"><a:noAutofit/></a:bodyPr><a:lstStyle/><a:p><a:pPr marL="0" lvl="0" indent="0" algn="l" defTabSz="622300"><a:lnSpc><a:spcPct val="90000"/></a:lnSpc><a:spcBef><a:spcPct val="0"/></a:spcBef><a:spcAft><a:spcPct val="35000"/></a:spcAft><a:buNone/></a:pPr><a:r><a:rPr lang="en-US" sz="1400" kern="1200" dirty="0"><a:latin typeface="Arial" panose="020B0604020202020204" pitchFamily="34" charset="0"/><a:cs typeface="Arial" panose="020B0604020202020204" pitchFamily="34" charset="0"/></a:rPr><a:t>Select appropriate architectural patterns for ML systems</a:t></a:r></a:p></dsp:txBody><dsp:txXfrm><a:off x="0" y="357605"/><a:ext cx="5192078" cy="356559"/></dsp:txXfrm></dsp:sp><dsp:sp modelId="{A6825BD3-BD29-7A4B-9770-DD11845469A5}"><dsp:nvSpPr><dsp:cNvPr id="0" name=""/><dsp:cNvSpPr/></dsp:nvSpPr><dsp:spPr><a:xfrm><a:off x="0" y="714165"/><a:ext cx="5192078" cy="0"/></a:xfrm><a:prstGeom prst="line"><a:avLst/></a:prstGeom><a:solidFill><a:schemeClr val="lt1"><a:hueOff val="0"/><a:satOff val="0"/><a:lumOff val="0"/><a:alphaOff val="0"/></a:schemeClr></a:solidFill><a:ln w="25400" cap="flat" cmpd="sng" algn="ctr"><a:solidFill><a:schemeClr val="accent6"><a:shade val="80000"/><a:hueOff val="0"/><a:satOff val="0"/><a:lumOff val="0"/><a:alphaOff val="0"/></a:schemeClr></a:solidFill><a:prstDash val="solid"/></a:ln><a:effectLst><a:outerShdw blurRad="40000" dist="20000" dir="5400000" rotWithShape="0"><a:srgbClr val="000000"><a:alpha val="38000"/></a:srgbClr></a:outerShdw></a:effectLst></dsp:spPr><dsp:style><a:lnRef idx="2"><a:scrgbClr r="0" g="0" b="0"/></a:lnRef><a:fillRef idx="1"><a:scrgbClr r="0" g="0" b="0"/></a:fillRef><a:effectRef idx="1"><a:scrgbClr r="0" g="0" b="0"/></a:effectRef><a:fontRef idx="minor"><a:schemeClr val="lt1"/></a:fontRef></dsp:style></dsp:sp><dsp:sp modelId="{C39AA2BE-D9B6-104C-87BC-22D5BD8658C1}"><dsp:nvSpPr><dsp:cNvPr id="0" name=""/><dsp:cNvSpPr/></dsp:nvSpPr><dsp:spPr><a:xfrm><a:off x="0" y="714165"/><a:ext cx="5192078" cy="356559"/></a:xfrm><a:prstGeom prst="rect"><a:avLst/></a:prstGeom><a:noFill/><a:ln><a:noFill/></a:ln><a:effectLst/></dsp:spPr><dsp:style><a:lnRef idx="0"><a:scrgbClr r="0" g="0" b="0"/></a:lnRef><a:fillRef idx="0"><a:scrgbClr r="0" g="0" b="0"/></a:fillRef><a:effectRef idx="0"><a:scrgbClr r="0" g="0" b="0"/></a:effectRef><a:fontRef idx="minor"/></dsp:style><dsp:txBody><a:bodyPr spcFirstLastPara="0" vert="horz" wrap="square" lIns="53340" tIns="53340" rIns="53340" bIns="53340" numCol="1" spcCol="1270" anchor="t" anchorCtr="0"><a:noAutofit/></a:bodyPr><a:lstStyle/><a:p><a:pPr marL="0" lvl="0" indent="0" algn="l" defTabSz="622300"><a:lnSpc><a:spcPct val="90000"/></a:lnSpc><a:spcBef><a:spcPct val="0"/></a:spcBef><a:spcAft><a:spcPct val="35000"/></a:spcAft><a:buNone/></a:pPr><a:r><a:rPr lang="en-US" sz="1400" kern="1200" dirty="0"><a:latin typeface="Arial" panose="020B0604020202020204" pitchFamily="34" charset="0"/><a:cs typeface="Arial" panose="020B0604020202020204" pitchFamily="34" charset="0"/></a:rPr><a:t>Make informed decisions about infrastructure choices</a:t></a:r></a:p></dsp:txBody><dsp:txXfrm><a:off x="0" y="714165"/><a:ext cx="5192078" cy="356559"/></dsp:txXfrm></dsp:sp><dsp:sp modelId="{B2F72576-6B55-4444-B1C6-37C60483938E}"><dsp:nvSpPr><dsp:cNvPr id="0" name=""/><dsp:cNvSpPr/></dsp:nvSpPr><dsp:spPr><a:xfrm><a:off x="0" y="1070725"/><a:ext cx="5192078" cy="0"/></a:xfrm><a:prstGeom prst="line"><a:avLst/></a:prstGeom><a:solidFill><a:schemeClr val="lt1"><a:hueOff val="0"/><a:satOff val="0"/><a:lumOff val="0"/><a:alphaOff val="0"/></a:schemeClr></a:solidFill><a:ln w="25400" cap="flat" cmpd="sng" algn="ctr"><a:solidFill><a:schemeClr val="accent6"><a:shade val="80000"/><a:hueOff val="0"/><a:satOff val="0"/><a:lumOff val="0"/><a:alphaOff val="0"/></a:schemeClr></a:solidFill><a:prstDash val="solid"/></a:ln><a:effectLst><a:outerShdw blurRad="40000" dist="20000" dir="5400000" rotWithShape="0"><a:srgbClr val="000000"><a:alpha val="38000"/></a:srgbClr></a:outerShdw></a:effectLst></dsp:spPr><dsp:style><a:lnRef idx="2"><a:scrgbClr r="0" g="0" b="0"/></a:lnRef><a:fillRef idx="1"><a:scrgbClr r="0" g="0" b="0"/></a:fillRef><a:effectRef idx="1"><a:scrgbClr r="0" g="0" b="0"/></a:effectRef><a:fontRef idx="minor"><a:schemeClr val="lt1"/></a:fontRef></dsp:style></dsp:sp><dsp:sp modelId="{379BD9A4-7DD5-2246-BB48-CAED3D8D54BE}"><dsp:nvSpPr><dsp:cNvPr id="0" name=""/><dsp:cNvSpPr/></dsp:nvSpPr><dsp:spPr><a:xfrm><a:off x="0" y="1070725"/><a:ext cx="5192078" cy="356559"/></a:xfrm><a:prstGeom prst="rect"><a:avLst/></a:prstGeom><a:noFill/><a:ln><a:noFill/></a:ln><a:effectLst/></dsp:spPr><dsp:style><a:lnRef idx="0"><a:scrgbClr r="0" g="0" b="0"/></a:lnRef><a:fillRef idx="0"><a:scrgbClr r="0" g="0" b="0"/></a:fillRef><a:effectRef idx="0"><a:scrgbClr r="0" g="0" b="0"/></a:effectRef><a:fontRef idx="minor"/></dsp:style><dsp:txBody><a:bodyPr spcFirstLastPara="0" vert="horz" wrap="square" lIns="53340" tIns="53340" rIns="53340" bIns="53340" numCol="1" spcCol="1270" anchor="t" anchorCtr="0"><a:noAutofit/></a:bodyPr><a:lstStyle/><a:p><a:pPr marL="0" lvl="0" indent="0" algn="l" defTabSz="622300"><a:lnSpc><a:spcPct val="90000"/></a:lnSpc><a:spcBef><a:spcPct val="0"/></a:spcBef><a:spcAft><a:spcPct val="35000"/></a:spcAft><a:buNone/></a:pPr><a:r><a:rPr lang="en-US" sz="1400" kern="1200" dirty="0"><a:latin typeface="Arial" panose="020B0604020202020204" pitchFamily="34" charset="0"/><a:cs typeface="Arial" panose="020B0604020202020204" pitchFamily="34" charset="0"/></a:rPr><a:t>Analyze trade-offs between architectural choices</a:t></a:r></a:p></dsp:txBody><dsp:txXfrm><a:off x="0" y="1070725"/><a:ext cx="5192078" cy="356559"/></dsp:txXfrm></dsp:sp><dsp:sp modelId="{0CE47D7F-D0BC-424A-99B4-46946834C261}"><dsp:nvSpPr><dsp:cNvPr id="0" name=""/><dsp:cNvSpPr/></dsp:nvSpPr><dsp:spPr><a:xfrm><a:off x="0" y="1427285"/><a:ext cx="5192078" cy="0"/></a:xfrm><a:prstGeom prst="line"><a:avLst/></a:prstGeom><a:solidFill><a:schemeClr val="lt1"><a:hueOff val="0"/><a:satOff val="0"/><a:lumOff val="0"/><a:alphaOff val="0"/></a:schemeClr></a:solidFill><a:ln w="25400" cap="flat" cmpd="sng" algn="ctr"><a:solidFill><a:schemeClr val="accent6"><a:shade val="80000"/><a:hueOff val="0"/><a:satOff val="0"/><a:lumOff val="0"/><a:alphaOff val="0"/></a:schemeClr></a:solidFill><a:prstDash val="solid"/></a:ln><a:effectLst><a:outerShdw blurRad="40000" dist="20000" dir="5400000" rotWithShape="0"><a:srgbClr val="000000"><a:alpha val="38000"/></a:srgbClr></a:outerShdw></a:effectLst></dsp:spPr><dsp:style><a:lnRef idx="2"><a:scrgbClr r="0" g="0" b="0"/></a:lnRef><a:fillRef idx="1"><a:scrgbClr r="0" g="0" b="0"/></a:fillRef><a:effectRef idx="1"><a:scrgbClr r="0" g="0" b="0"/></a:effectRef><a:fontRef idx="minor"><a:schemeClr val="lt1"/></a:fontRef></dsp:style></dsp:sp><dsp:sp modelId="{CEC5BC5D-E7DD-1340-89AE-11BCA32A219E}"><dsp:nvSpPr><dsp:cNvPr id="0" name=""/><dsp:cNvSpPr/></dsp:nvSpPr><dsp:spPr><a:xfrm><a:off x="0" y="1427285"/><a:ext cx="5192078" cy="356559"/></a:xfrm><a:prstGeom prst="rect"><a:avLst/></a:prstGeom><a:noFill/><a:ln><a:noFill/></a:ln><a:effectLst/></dsp:spPr><dsp:style><a:lnRef idx="0"><a:scrgbClr r="0" g="0" b="0"/></a:lnRef><a:fillRef idx="0"><a:scrgbClr r="0" g="0" b="0"/></a:fillRef><a:effectRef idx="0"><a:scrgbClr r="0" g="0" b="0"/></a:effectRef><a:fontRef idx="minor"/></dsp:style><dsp:txBody><a:bodyPr spcFirstLastPara="0" vert="horz" wrap="square" lIns="53340" tIns="53340" rIns="53340" bIns="53340" numCol="1" spcCol="1270" anchor="t" anchorCtr="0"><a:noAutofit/></a:bodyPr><a:lstStyle/><a:p><a:pPr marL="0" lvl="0" indent="0" algn="l" defTabSz="622300"><a:lnSpc><a:spcPct val="90000"/></a:lnSpc><a:spcBef><a:spcPct val="0"/></a:spcBef><a:spcAft><a:spcPct val="35000"/></a:spcAft><a:buNone/></a:pPr><a:r><a:rPr lang="en-US" sz="1400" kern="1200" dirty="0"><a:latin typeface="Arial" panose="020B0604020202020204" pitchFamily="34" charset="0"/><a:cs typeface="Arial" panose="020B0604020202020204" pitchFamily="34" charset="0"/></a:rPr><a:t>Design for scalability and maintainability</a:t></a:r></a:p></dsp:txBody><dsp:txXfrm><a:off x="0" y="1427285"/><a:ext cx="5192078" cy="356559"/></dsp:txXfrm></dsp:sp><dsp:sp modelId="{196CA4F1-AF41-7842-93A3-F0DDDF8DEF92}"><dsp:nvSpPr><dsp:cNvPr id="0" name=""/><dsp:cNvSpPr/></dsp:nvSpPr><dsp:spPr><a:xfrm><a:off x="0" y="1783845"/><a:ext cx="5192078" cy="0"/></a:xfrm><a:prstGeom prst="line"><a:avLst/></a:prstGeom><a:solidFill><a:schemeClr val="lt1"><a:hueOff val="0"/><a:satOff val="0"/><a:lumOff val="0"/><a:alphaOff val="0"/></a:schemeClr></a:solidFill><a:ln w="25400" cap="flat" cmpd="sng" algn="ctr"><a:solidFill><a:schemeClr val="accent6"><a:shade val="80000"/><a:hueOff val="0"/><a:satOff val="0"/><a:lumOff val="0"/><a:alphaOff val="0"/></a:schemeClr></a:solidFill><a:prstDash val="solid"/></a:ln><a:effectLst><a:outerShdw blurRad="40000" dist="20000" dir="5400000" rotWithShape="0"><a:srgbClr val="000000"><a:alpha val="38000"/></a:srgbClr></a:outerShdw></a:effectLst></dsp:spPr><dsp:style><a:lnRef idx="2"><a:scrgbClr r="0" g="0" b="0"/></a:lnRef><a:fillRef idx="1"><a:scrgbClr r="0" g="0" b="0"/></a:fillRef><a:effectRef idx="1"><a:scrgbClr r="0" g="0" b="0"/></a:effectRef><a:fontRef idx="minor"><a:schemeClr val="lt1"/></a:fontRef></dsp:style></dsp:sp><dsp:sp modelId="{4C63902F-8E66-7941-9A32-7B9A4C133799}"><dsp:nvSpPr><dsp:cNvPr id="0" name=""/><dsp:cNvSpPr/></dsp:nvSpPr><dsp:spPr><a:xfrm><a:off x="0" y="1783845"/><a:ext cx="5192078" cy="356559"/></a:xfrm><a:prstGeom prst="rect"><a:avLst/></a:prstGeom><a:noFill/><a:ln><a:noFill/></a:ln><a:effectLst/></dsp:spPr><dsp:style><a:lnRef idx="0"><a:scrgbClr r="0" g="0" b="0"/></a:lnRef><a:fillRef idx="0"><a:scrgbClr r="0" g="0" b="0"/></a:fillRef><a:effectRef idx="0"><a:scrgbClr r="0" g="0" b="0"/></a:effectRef><a:fontRef idx="minor"/></dsp:style><dsp:txBody><a:bodyPr spcFirstLastPara="0" vert="horz" wrap="square" lIns="53340" tIns="53340" rIns="53340" bIns="53340" numCol="1" spcCol="1270" anchor="t" anchorCtr="0"><a:noAutofit/></a:bodyPr><a:lstStyle/><a:p><a:pPr marL="0" lvl="0" indent="0" algn="l" defTabSz="622300"><a:lnSpc><a:spcPct val="90000"/></a:lnSpc><a:spcBef><a:spcPct val="0"/></a:spcBef><a:spcAft><a:spcPct val="35000"/></a:spcAft><a:buNone/></a:pPr><a:r><a:rPr lang="en-US" sz="1400" kern="1200"><a:latin typeface="Arial" panose="020B0604020202020204" pitchFamily="34" charset="0"/><a:cs typeface="Arial" panose="020B0604020202020204" pitchFamily="34" charset="0"/></a:rPr><a:t>Document architecture decisions with justification</a:t></a:r><a:endParaRPr lang="en-US" sz="1400" kern="1200" dirty="0"><a:latin typeface="Arial" panose="020B0604020202020204" pitchFamily="34" charset="0"/><a:cs typeface="Arial" panose="020B0604020202020204" pitchFamily="34" charset="0"/></a:endParaRPr></a:p></dsp:txBody><dsp:txXfrm><a:off x="0" y="1783845"/><a:ext cx="5192078" cy="356559"/></dsp:txXfrm></dsp:sp></dsp:spTree></dsp:drawing>