<?xml version="1.0" encoding="UTF-8" standalone="yes"?>
<p:sld xmlns:a="http://schemas.openxmlformats.org/drawingml/2006/main" xmlns:r="http://schemas.openxmlformats.org/officeDocument/2006/relationships" xmlns:p="http://schemas.openxmlformats.org/presentationml/2006/main"><p:cSld><p:spTree><p:nvGrpSpPr><p:cNvPr id="1" name="Shape 56"/><p:cNvGrpSpPr/><p:nvPr/></p:nvGrpSpPr><p:grpSpPr><a:xfrm><a:off x="0" y="0"/><a:ext cx="0" cy="0"/><a:chOff x="0" y="0"/><a:chExt cx="0" cy="0"/></a:xfrm></p:grpSpPr><p:sp><p:nvSpPr><p:cNvPr id="57" name="Google Shape;57;p7"/><p:cNvSpPr txBox="1"><a:spLocks noGrp="1"/></p:cNvSpPr><p:nvPr><p:ph type="title"/></p:nvPr></p:nvSpPr><p:spPr><a:xfrm><a:off x="139147" y="831722"/><a:ext cx="5326095" cy="560405"/></a:xfrm><a:prstGeom prst="rect"><a:avLst/></a:prstGeom><a:noFill/><a:ln><a:noFill/></a:ln></p:spPr><p:txBody><a:bodyPr spcFirstLastPara="1" wrap="square" lIns="0" tIns="189225" rIns="0" bIns="0" anchor="t" anchorCtr="0"><a:spAutoFit/></a:bodyPr><a:lstStyle/><a:p><a:pPr lvl="0"/><a:r><a:rPr lang="en-US" sz="2400" dirty="0"/><a:t>ARCHITECTURE &amp; SYSTEM DESIGN</a:t></a:r><a:endParaRPr sz="3000" dirty="0"><a:latin typeface="Open Sans"/><a:ea typeface="Open Sans"/><a:cs typeface="Open Sans"/><a:sym typeface="Open Sans"/></a:endParaRPr></a:p></p:txBody></p:sp><p:grpSp><p:nvGrpSpPr><p:cNvPr id="58" name="Google Shape;58;p7"/><p:cNvGrpSpPr/><p:nvPr/></p:nvGrpSpPr><p:grpSpPr><a:xfrm><a:off x="1726" y="2966211"/><a:ext cx="5760046" cy="25400"/><a:chOff x="139" y="2966211"/><a:chExt cx="5760046" cy="25400"/></a:xfrm></p:grpSpPr><p:sp><p:nvSpPr><p:cNvPr id="59" name="Google Shape;59;p7"/><p:cNvSpPr/><p:nvPr/></p:nvSpPr><p:spPr><a:xfrm><a:off x="1926247" y="2966211"/><a:ext cx="1917064" cy="25400"/></a:xfrm><a:custGeom><a:avLst/><a:gdLst/><a:ahLst/><a:cxnLst/><a:rect l="l" t="t" r="r" b="b"/><a:pathLst><a:path w="1917064" h="25400" extrusionOk="0"><a:moveTo><a:pt x="1916887" y="0"/></a:moveTo><a:lnTo><a:pt x="0" y="0"/></a:lnTo><a:lnTo><a:pt x="0" y="25209"/></a:lnTo><a:lnTo><a:pt x="1916887" y="25209"/></a:lnTo><a:lnTo><a:pt x="1916887" y="0"/></a:lnTo><a:close/></a:path></a:pathLst></a:custGeom><a:solidFill><a:srgbClr val="FFFFFF"/></a:solidFill><a:ln><a:noFill/></a:ln></p:spPr><p:txBody><a:bodyPr spcFirstLastPara="1" wrap="square" lIns="0" tIns="0" rIns="0" bIns="0" anchor="t" anchorCtr="0"><a:noAutofit/></a:bodyPr><a:lstStyle/><a:p><a:endParaRPr sz="1800"><a:solidFill><a:schemeClr val="dk1"/></a:solidFill><a:latin typeface="Calibri"/><a:ea typeface="Calibri"/><a:cs typeface="Calibri"/><a:sym typeface="Calibri"/></a:endParaRPr></a:p></p:txBody></p:sp><p:sp><p:nvSpPr><p:cNvPr id="60" name="Google Shape;60;p7"/><p:cNvSpPr/><p:nvPr/></p:nvSpPr><p:spPr><a:xfrm><a:off x="3843121" y="2966211"/><a:ext cx="1917064" cy="25400"/></a:xfrm><a:custGeom><a:avLst/><a:gdLst/><a:ahLst/><a:cxnLst/><a:rect l="l" t="t" r="r" b="b"/><a:pathLst><a:path w="1917064" h="25400" extrusionOk="0"><a:moveTo><a:pt x="1916874" y="0"/></a:moveTo><a:lnTo><a:pt x="0" y="0"/></a:lnTo><a:lnTo><a:pt x="0" y="25209"/></a:lnTo><a:lnTo><a:pt x="1916874" y="25209"/></a:lnTo><a:lnTo><a:pt x="1916874" y="0"/></a:lnTo><a:close/></a:path></a:pathLst></a:custGeom><a:solidFill><a:srgbClr val="F17225"/></a:solidFill><a:ln><a:noFill/></a:ln></p:spPr><p:txBody><a:bodyPr spcFirstLastPara="1" wrap="square" lIns="0" tIns="0" rIns="0" bIns="0" anchor="t" anchorCtr="0"><a:noAutofit/></a:bodyPr><a:lstStyle/><a:p><a:endParaRPr sz="1800"><a:solidFill><a:schemeClr val="dk1"/></a:solidFill><a:latin typeface="Calibri"/><a:ea typeface="Calibri"/><a:cs typeface="Calibri"/><a:sym typeface="Calibri"/></a:endParaRPr></a:p></p:txBody></p:sp><p:sp><p:nvSpPr><p:cNvPr id="61" name="Google Shape;61;p7"/><p:cNvSpPr/><p:nvPr/></p:nvSpPr><p:spPr><a:xfrm><a:off x="139" y="2966211"/><a:ext cx="1926589" cy="25400"/></a:xfrm><a:custGeom><a:avLst/><a:gdLst/><a:ahLst/><a:cxnLst/><a:rect l="l" t="t" r="r" b="b"/><a:pathLst><a:path w="1926589" h="25400" extrusionOk="0"><a:moveTo><a:pt x="1926107" y="0"/></a:moveTo><a:lnTo><a:pt x="0" y="0"/></a:lnTo><a:lnTo><a:pt x="0" y="25209"/></a:lnTo><a:lnTo><a:pt x="1926107" y="25209"/></a:lnTo><a:lnTo><a:pt x="1926107" y="0"/></a:lnTo><a:close/></a:path></a:pathLst></a:custGeom><a:solidFill><a:srgbClr val="C0C4CA"><a:alpha val="89803"/></a:srgbClr></a:solidFill><a:ln><a:noFill/></a:ln></p:spPr><p:txBody><a:bodyPr spcFirstLastPara="1" wrap="square" lIns="0" tIns="0" rIns="0" bIns="0" anchor="t" anchorCtr="0"><a:noAutofit/></a:bodyPr><a:lstStyle/><a:p><a:endParaRPr sz="1800"><a:solidFill><a:schemeClr val="dk1"/></a:solidFill><a:latin typeface="Calibri"/><a:ea typeface="Calibri"/><a:cs typeface="Calibri"/><a:sym typeface="Calibri"/></a:endParaRPr></a:p></p:txBody></p:sp></p:grpSp><p:sp><p:nvSpPr><p:cNvPr id="68" name="Google Shape;68;p7"/><p:cNvSpPr txBox="1"/><p:nvPr/></p:nvSpPr><p:spPr><a:xfrm><a:off x="538149" y="2391959"/><a:ext cx="1688464" cy="284309"/></a:xfrm><a:prstGeom prst="rect"><a:avLst/></a:prstGeom><a:noFill/><a:ln><a:noFill/></a:ln></p:spPr><p:txBody><a:bodyPr spcFirstLastPara="1" wrap="square" lIns="0" tIns="12700" rIns="0" bIns="0" anchor="t" anchorCtr="0"><a:spAutoFit/></a:bodyPr><a:lstStyle/><a:p><a:pPr marL="12700" marR="5080"><a:lnSpc><a:spcPct val="126400"/></a:lnSpc></a:pPr><a:r><a:rPr lang="en-US" sz="700"><a:solidFill><a:srgbClr val="FFFFFF"/></a:solidFill><a:latin typeface="Open Sans"/><a:ea typeface="Open Sans"/><a:cs typeface="Open Sans"/><a:sym typeface="Open Sans"/></a:rPr><a:t>Nhà C, Tòa Nhà Việt Úc, Lưu Hữu Phước,  Quận Nam Từ Liêm, Hà Nội</a:t></a:r><a:endParaRPr sz="700"><a:solidFill><a:schemeClr val="dk1"/></a:solidFill><a:latin typeface="Open Sans"/><a:ea typeface="Open Sans"/><a:cs typeface="Open Sans"/><a:sym typeface="Open Sans"/></a:endParaRPr></a:p></p:txBody></p:sp><p:sp><p:nvSpPr><p:cNvPr id="3" name="Slide Number Placeholder 2"><a:extLst><a:ext uri="{FF2B5EF4-FFF2-40B4-BE49-F238E27FC236}"><a16:creationId xmlns:a16="http://schemas.microsoft.com/office/drawing/2014/main" id="{D20F15E7-66EF-65F1-A789-D6DC830F4CBF}"/></a:ext></a:extLst></p:cNvPr><p:cNvSpPr><a:spLocks noGrp="1"/></p:cNvSpPr><p:nvPr><p:ph type="sldNum" idx="12"/></p:nvPr></p:nvSpPr><p:spPr/><p:txBody><a:bodyPr/><a:lstStyle/><a:p><a:fld id="{00000000-1234-1234-1234-123412341234}" type="slidenum"><a:rPr lang="en-US" smtClean="0"/><a:pPr/><a:t>1</a:t></a:fld><a:endParaRPr lang="en-US"/></a:p></p:txBody></p:sp></p:spTree></p:cSld><p:clrMapOvr><a:masterClrMapping/></p:clrMapOvr></p:sld>